fastxm-0.1.5.dist-info/METADATA
fastxm-0.1.5.dist-info/WHEEL
fastxm/__init__.py
fastxm/fastxm.cpython-38-darwin.so
fastxm-0.1.5.dist-info/RECORD
